[
  {
    "3TLfaUYwcc8_0_7724500000000001_10_7724_94949671": {
      "category": "direct_perception",
      "difficulty": "basic",
      "question": "Is there spoken content in this audio?",
      "answer": "Yes, a female voice speaks continuously throughout the recording.",
      "domain": "S00"
    }
  },
  {
    "3TLfaUYwcc8_0_7724500000000001_10_7724_7b9e6fac": {
      "category": "sound_characteristics",
      "difficulty": "intermediate",
      "question": "How would you describe the speaker's emotional tone?",
      "answer": "The voice carries enthusiastic inflection with positive emotional valence.",
      "domain": "S00"
    }
  },
  {
    "3TLfaUYwcc8_0_7724500000000001_10_7724_37483bd7": {
      "category": "environment_reasoning",
      "difficulty": "advanced",
      "question": "What type of recording environment does this suggest?",
      "answer": "A controlled indoor space with proximity to recording equipment.",
      "domain": "S00"
    }
  },
  {
    "3TLfaUYwcc8_0_7724500000000001_10_7724_21937c3d": {
      "category": "inference_judgement",
      "difficulty": "complex",
      "question": "What communication purpose does this audio most likely serve?",
      "answer": "Personal commentary or content creation narration.",
      "domain": "S00"
    }
  },
  {
    "3TLfaUYwcc8_0_7724500000000001_10_7724_ea06a91b": {
      "category": "quality_assessment",
      "difficulty": "intermediate",
      "question": "Are there any notable technical imperfections?",
      "answer": "Subtle background interference present without disrupting speech clarity.",
      "domain": "S00"
    }
  }
]